setup.py
./example/django_rapidprototype/__init__.py
./example/django_rapidprototype/settings.py
./example/django_rapidprototype/urls.py
./example/django_rapidprototype/wsgi.py
./example/drpexamples/__init__.py
./example/drpexamples/admin.py
./example/drpexamples/apps.py
./example/drpexamples/models.py
./example/drpexamples/tests.py
./example/drpexamples/urls.py
./example/drpexamples/views.py
./example/drpexamples/migrations/__init__.py
./rapidprototype/__init__.py
./rapidprototype/admin.py
./rapidprototype/apps.py
./rapidprototype/forms.py
./rapidprototype/models.py
./rapidprototype/tests.py
./rapidprototype/urls.py
./rapidprototype/utils.py
./rapidprototype/views.py
./rapidprototype/core/__init__.py
./rapidprototype/core/default_settings.py
./rapidprototype/migrations/__init__.py
rapidprototype.egg-info/PKG-INFO
rapidprototype.egg-info/SOURCES.txt
rapidprototype.egg-info/dependency_links.txt
rapidprototype.egg-info/requires.txt
rapidprototype.egg-info/top_level.txt