Metadata-Version: 1.1
Name: rapidprototype
Version: 0.1.3
Summary: Library for create easy prototypes with django
Home-page: https://github.com/minrock/django_rapidprototype
Author: minrock
Author-email: lmoncarisg@gmail.com
License: BSD
Download-URL: https://github.com/minrock/django_rapidprototype/tarball/0.1.3/
Keywords: Django prototype html
Platform: UNKNOWN
Classifier: Framework :: Django
Classifier: Topic :: Utilities
